moderngl_window/__init__.py
moderngl_window/exceptions.py
moderngl_window/py.typed
moderngl_window/screenshot.py
moderngl_window/atlas/__init__.py
moderngl_window/atlas/base.py
moderngl_window/atlas/simple_atlas.py
moderngl_window/capture/__init__.py
moderngl_window/capture/base.py
moderngl_window/capture/ffmpeg.py
moderngl_window/conf/__init__.py
moderngl_window/conf/default.py
moderngl_window/context/__init__.py
moderngl_window/context/base/__init__.py
moderngl_window/context/base/keys.py
moderngl_window/context/base/window.py
moderngl_window/context/glfw/__init__.py
moderngl_window/context/glfw/keys.py
moderngl_window/context/glfw/window.py
moderngl_window/context/headless/__init__.py
moderngl_window/context/headless/keys.py
moderngl_window/context/headless/window.py
moderngl_window/context/pygame2/__init__.py
moderngl_window/context/pygame2/keys.py
moderngl_window/context/pygame2/window.py
moderngl_window/context/pyglet/__init__.py
moderngl_window/context/pyglet/keys.py
moderngl_window/context/pyglet/window.py
moderngl_window/context/pyqt5/__init__.py
moderngl_window/context/pyqt5/keys.py
moderngl_window/context/pyqt5/window.py
moderngl_window/context/pyside2/__init__.py
moderngl_window/context/pyside2/keys.py
moderngl_window/context/pyside2/window.py
moderngl_window/context/sdl2/__init__.py
moderngl_window/context/sdl2/keys.py
moderngl_window/context/sdl2/window.py
moderngl_window/context/tk/__init__.py
moderngl_window/context/tk/keys.py
moderngl_window/context/tk/window.py
moderngl_window/finders/__init__.py
moderngl_window/finders/base.py
moderngl_window/finders/data.py
moderngl_window/finders/program.py
moderngl_window/finders/scene.py
moderngl_window/finders/texture.py
moderngl_window/geometry/__init__.py
moderngl_window/geometry/attributes.py
moderngl_window/geometry/bbox.py
moderngl_window/geometry/cube.py
moderngl_window/geometry/quad.py
moderngl_window/geometry/sphere.py
moderngl_window/integrations/__init__.py
moderngl_window/integrations/imgui.py
moderngl_window-3.0.2.dist-info/LICENSE
moderngl_window-3.0.2.dist-info/METADATA
moderngl_window-3.0.2.dist-info/WHEEL
moderngl_window-3.0.2.dist-info/top_level.txt
moderngl_window-3.0.2.dist-info/RECORD
