Metadata-Version: 2.1
Name: moderngl-window
Version: 3.0.2
Summary: A cross platform helper library for ModernGL making window creation and resource loading simple
Author-email: Einar Forselv <eforselv@gmail.com>
Project-URL: Source, https://github.com/moderngl/moderngl_window
Project-URL: Documentation, https://moderngl-window.readthedocs.io
Project-URL: ModernGL, https://github.com/moderngl/moderngl
Classifier: License :: OSI Approved :: MIT License
Classifier: Operating System :: OS Independent
Classifier: Topic :: Games/Entertainment
Classifier: Topic :: Multimedia :: Graphics
Classifier: Topic :: Multimedia :: Graphics :: 3D Rendering
Classifier: Topic :: Scientific/Engineering :: Visualization
Classifier: Programming Language :: Python :: 3 :: Only
Classifier: Programming Language :: Python :: 3.9
Classifier: Programming Language :: Python :: 3.10
Classifier: Programming Language :: Python :: 3.11
Classifier: Programming Language :: Python :: 3.12
Classifier: Programming Language :: Python :: 3.13
Requires-Python: >=3.9
License-File: LICENSE
Requires-Dist: moderngl<6
Requires-Dist: pyglet>=2.0.0
Requires-Dist: numpy
Requires-Dist: pyglm<3,>=2.7.0
Requires-Dist: Pillow>=10.0.1
Provides-Extra: dev
Requires-Dist: pytest; extra == "dev"
Requires-Dist: mypy; extra == "dev"
Requires-Dist: coverage; extra == "dev"
Requires-Dist: pywavefront; extra == "dev"
Requires-Dist: trimesh; extra == "dev"
Requires-Dist: scipy; extra == "dev"
Requires-Dist: build; extra == "dev"
Requires-Dist: ruff; extra == "dev"
Provides-Extra: docs
Requires-Dist: Sphinx~=8.1.3; extra == "docs"
Requires-Dist: sphinx-rtd-theme~=3.0.1; extra == "docs"
Requires-Dist: sphinx-rtd-dark-mode==1.3.0; extra == "docs"
Requires-Dist: doc8; extra == "docs"
Provides-Extra: imgui
Requires-Dist: imgui-bundle; extra == "imgui"
Provides-Extra: pygame
Requires-Dist: pygame>=2.0.1; extra == "pygame"
Provides-Extra: pygame-ce
Requires-Dist: pygame-ce>=2.0.1; extra == "pygame-ce"
Provides-Extra: tk
Requires-Dist: pyopengltk>=0.0.3; extra == "tk"
Provides-Extra: trimesh
Requires-Dist: trimesh>=3.2.6; extra == "trimesh"
Provides-Extra: pywavefront
Requires-Dist: pywavefront<2,>=1.2.0; extra == "pywavefront"
Provides-Extra: pysdl2
Requires-Dist: PySDL2; extra == "pysdl2"
Provides-Extra: glfw
Requires-Dist: glfw; extra == "glfw"
Provides-Extra: pyqt5
Requires-Dist: PyQt5; extra == "pyqt5"
Provides-Extra: pyside2
Requires-Dist: PySide2<6; extra == "pyside2"
Provides-Extra: pdf
Requires-Dist: ReportLab>=1.2; extra == "pdf"
